[
  {
    "item_number": 1,
    "text": "ITEM 1. THE FRANCHISOR AND ANY PARENTS, PREDECESSORS AND AFFILIATES",
    "match_scores": {
      "full": 97.63779527559055,
      "label": 100,
      "keywords": 0.0,
      "final": 83.29602182080181
    },
    "page_number": 8,
    "node_index": 55,
    "start_node_index": 55,
    "end_node_index": 91,
    "start_page": 8,
    "end_page": 11,
    "alignment_score": 0.8954248366013072,
    "pdf_file_path": "C:\\Users\\mille\\OneDrive\\FDD_PDFS\\MINERU\\Budget_Blinds_LLC_FDD_2024_ID636427.pdf-96195de9-ed27-4de5-8f22-02f622605df9\\199524c0-3f73-405e-a873-9739e59be7e6_origin.pdf"
  },
  {
    "item_number": 2,
    "text": "ITEM 2. BUSINESS EXPERIENCE",
    "match_scores": {
      "full": 96.29629629629629,
      "label": 100,
      "keywords": 0.0,
      "final": 80.83605664488017
    },
    "page_number": 11,
    "node_index": 92,
    "start_node_index": 92,
    "end_node_index": 123,
    "start_page": 11,
    "end_page": 13,
    "alignment_score": 0.5375816993464052,
    "pdf_file_path": "C:\\Users\\mille\\OneDrive\\FDD_PDFS\\MINERU\\Budget_Blinds_LLC_FDD_2024_ID636427.pdf-96195de9-ed27-4de5-8f22-02f622605df9\\199524c0-3f73-405e-a873-9739e59be7e6_origin.pdf"
  },
  {
    "item_number": 3,
    "text": "ITEM 3. LITIGATION",
    "match_scores": {
      "full": 94.44444444444444,
      "label": 100,
      "keywords": 0.0,
      "final": 79.38725490196079
    },
    "page_number": 13,
    "node_index": 124,
    "start_node_index": 124,
    "end_node_index": 133,
    "start_page": 13,
    "end_page": 14,
    "alignment_score": 0.43300653594771243,
    "pdf_file_path": "C:\\Users\\mille\\OneDrive\\FDD_PDFS\\MINERU\\Budget_Blinds_LLC_FDD_2024_ID636427.pdf-96195de9-ed27-4de5-8f22-02f622605df9\\199524c0-3f73-405e-a873-9739e59be7e6_origin.pdf"
  },
  {
    "item_number": 4,
    "text": "ITEM 4. BANKRUPTCY",
    "match_scores": {
      "full": 94.44444444444444,
      "label": 100,
      "keywords": 0.0,
      "final": 79.48529411764707
    },
    "page_number": 14,
    "node_index": 134,
    "start_node_index": 134,
    "end_node_index": 135,
    "start_page": 14,
    "end_page": 14,
    "alignment_score": 0.45261437908496727,
    "pdf_file_path": "C:\\Users\\mille\\OneDrive\\FDD_PDFS\\MINERU\\Budget_Blinds_LLC_FDD_2024_ID636427.pdf-96195de9-ed27-4de5-8f22-02f622605df9\\199524c0-3f73-405e-a873-9739e59be7e6_origin.pdf"
  },
  {
    "item_number": 5,
    "text": "ITEM 5. INITIAL FEES",
    "match_scores": {
      "full": 95.0,
      "label": 100,
      "keywords": 0.0,
      "final": 79.72222222222223
    },
    "page_number": 14,
    "node_index": 136,
    "start_node_index": 136,
    "end_node_index": 148,
    "start_page": 14,
    "end_page": 15,
    "alignment_score": 0.4444444444444444,
    "pdf_file_path": "C:\\Users\\mille\\OneDrive\\FDD_PDFS\\MINERU\\Budget_Blinds_LLC_FDD_2024_ID636427.pdf-96195de9-ed27-4de5-8f22-02f622605df9\\199524c0-3f73-405e-a873-9739e59be7e6_origin.pdf"
  },
  {
    "item_number": 6,
    "text": "ITEM 6. OTHER FEES",
    "match_scores": {
      "full": 94.44444444444444,
      "label": 100,
      "keywords": 0.0,
      "final": 79.41993464052288
    },
    "page_number": 15,
    "node_index": 149,
    "start_node_index": 149,
    "end_node_index": 164,
    "start_page": 15,
    "end_page": 19,
    "alignment_score": 0.4395424836601307,
    "pdf_file_path": "C:\\Users\\mille\\OneDrive\\FDD_PDFS\\MINERU\\Budget_Blinds_LLC_FDD_2024_ID636427.pdf-96195de9-ed27-4de5-8f22-02f622605df9\\199524c0-3f73-405e-a873-9739e59be7e6_origin.pdf"
  },
  {
    "item_number": 7,
    "text": "ITEM 7. ESTIMATED INITIAL INVESTMENT",
    "match_scores": {
      "full": 97.22222222222223,
      "label": 100,
      "keywords": 0.0,
      "final": 81.84640522875817
    },
    "page_number": 19,
    "node_index": 165,
    "start_node_index": 165,
    "end_node_index": 188,
    "start_page": 19,
    "end_page": 23,
    "alignment_score": 0.6470588235294117,
    "pdf_file_path": "C:\\Users\\mille\\OneDrive\\FDD_PDFS\\MINERU\\Budget_Blinds_LLC_FDD_2024_ID636427.pdf-96195de9-ed27-4de5-8f22-02f622605df9\\199524c0-3f73-405e-a873-9739e59be7e6_origin.pdf"
  },
  {
    "item_number": 8,
    "text": "ITEM 8. RESTRICTIONS ON SOURCES OF PRODUCTS AND SERVICES",
    "match_scores": {
      "full": 98.21428571428571,
      "label": 100,
      "keywords": 0.0,
      "final": 83.51073762838469
    },
    "page_number": 23,
    "node_index": 189,
    "start_node_index": 189,
    "end_node_index": 204,
    "start_page": 23,
    "end_page": 25,
    "alignment_score": 0.880718954248366,
    "pdf_file_path": "C:\\Users\\mille\\OneDrive\\FDD_PDFS\\MINERU\\Budget_Blinds_LLC_FDD_2024_ID636427.pdf-96195de9-ed27-4de5-8f22-02f622605df9\\199524c0-3f73-405e-a873-9739e59be7e6_origin.pdf"
  },
  {
    "item_number": 9,
    "text": "ITEM 9. FRANCHISEE'S OBLIGATIONS",
    "match_scores": {
      "full": 96.875,
      "label": 100,
      "keywords": 0.0,
      "final": 81.41952614379085
    },
    "page_number": 25,
    "node_index": 205,
    "start_node_index": 205,
    "end_node_index": 209,
    "start_page": 25,
    "end_page": 26,
    "alignment_score": 0.5964052287581699,
    "pdf_file_path": "C:\\Users\\mille\\OneDrive\\FDD_PDFS\\MINERU\\Budget_Blinds_LLC_FDD_2024_ID636427.pdf-96195de9-ed27-4de5-8f22-02f622605df9\\199524c0-3f73-405e-a873-9739e59be7e6_origin.pdf"
  },
  {
    "item_number": 10,
    "text": "ITEM 10. FINANCING",
    "match_scores": {
      "full": 94.44444444444444,
      "label": 100,
      "keywords": 0.0,
      "final": 79.39542483660131
    },
    "page_number": 26,
    "node_index": 210,
    "start_node_index": 210,
    "end_node_index": 218,
    "start_page": 26,
    "end_page": 27,
    "alignment_score": 0.434640522875817,
    "pdf_file_path": "C:\\Users\\mille\\OneDrive\\FDD_PDFS\\MINERU\\Budget_Blinds_LLC_FDD_2024_ID636427.pdf-96195de9-ed27-4de5-8f22-02f622605df9\\199524c0-3f73-405e-a873-9739e59be7e6_origin.pdf"
  },
  {
    "item_number": 11,
    "text": "ITEM 11. FRANCHISOR'S ASSISTANCE, ADVERTISING, COMPUTER SYSTEMS, AND TRAINING",
    "match_scores": {
      "full": 98.7012987012987,
      "label": 100,
      "keywords": 0.0,
      "final": 84.33430948136831
    },
    "page_number": 27,
    "node_index": 219,
    "start_node_index": 219,
    "end_node_index": 295,
    "start_page": 27,
    "end_page": 36,
    "alignment_score": 0.9967320261437909,
    "pdf_file_path": "C:\\Users\\mille\\OneDrive\\FDD_PDFS\\MINERU\\Budget_Blinds_LLC_FDD_2024_ID636427.pdf-96195de9-ed27-4de5-8f22-02f622605df9\\199524c0-3f73-405e-a873-9739e59be7e6_origin.pdf"
  },
  {
    "item_number": 12,
    "text": "ITEM 12. TERRITORY",
    "match_scores": {
      "full": 94.44444444444444,
      "label": 100,
      "keywords": 0.0,
      "final": 79.40359477124184
    },
    "page_number": 36,
    "node_index": 296,
    "start_node_index": 296,
    "end_node_index": 318,
    "start_page": 36,
    "end_page": 38,
    "alignment_score": 0.4362745098039216,
    "pdf_file_path": "C:\\Users\\mille\\OneDrive\\FDD_PDFS\\MINERU\\Budget_Blinds_LLC_FDD_2024_ID636427.pdf-96195de9-ed27-4de5-8f22-02f622605df9\\199524c0-3f73-405e-a873-9739e59be7e6_origin.pdf"
  },
  {
    "item_number": 13,
    "text": "ITEM 13. TRADEMARKS",
    "match_scores": {
      "full": 94.73684210526315,
      "label": 100,
      "keywords": 0.0,
      "final": 79.6641726866185
    },
    "page_number": 38,
    "node_index": 319,
    "start_node_index": 319,
    "end_node_index": 331,
    "start_page": 38,
    "end_page": 39,
    "alignment_score": 0.45915032679738566,
    "pdf_file_path": "C:\\Users\\mille\\OneDrive\\FDD_PDFS\\MINERU\\Budget_Blinds_LLC_FDD_2024_ID636427.pdf-96195de9-ed27-4de5-8f22-02f622605df9\\199524c0-3f73-405e-a873-9739e59be7e6_origin.pdf"
  },
  {
    "item_number": 14,
    "text": "ITEM 14. PATENTS, COPYRIGHTS AND PROPRIETARY INFORMATION",
    "match_scores": {
      "full": 97.34513274336283,
      "label": 100,
      "keywords": 0.0,
      "final": 83.15786048932847
    },
    "page_number": 39,
    "node_index": 332,
    "start_node_index": 332,
    "end_node_index": 337,
    "start_page": 39,
    "end_page": 40,
    "alignment_score": 0.8970588235294118,
    "pdf_file_path": "C:\\Users\\mille\\OneDrive\\FDD_PDFS\\MINERU\\Budget_Blinds_LLC_FDD_2024_ID636427.pdf-96195de9-ed27-4de5-8f22-02f622605df9\\199524c0-3f73-405e-a873-9739e59be7e6_origin.pdf"
  },
  {
    "item_number": 15,
    "text": "ITEM 15. OBLIGATION TO PARTICIPATE IN THE ACTUAL OPERATION OF THE FRANCHISED BUSINESS",
    "match_scores": {
      "full": 98.13664596273291,
      "label": 100,
      "keywords": 0.0,
      "final": 83.99479356960175
    },
    "page_number": 40,
    "node_index": 338,
    "start_node_index": 338,
    "end_node_index": 340,
    "start_page": 40,
    "end_page": 40,
    "alignment_score": 0.9852941176470589,
    "pdf_file_path": "C:\\Users\\mille\\OneDrive\\FDD_PDFS\\MINERU\\Budget_Blinds_LLC_FDD_2024_ID636427.pdf-96195de9-ed27-4de5-8f22-02f622605df9\\199524c0-3f73-405e-a873-9739e59be7e6_origin.pdf"
  },
  {
    "item_number": 16,
    "text": "ITEM 16. RESTRICTION ON WHAT FRANCHISEE MAY SELL",
    "match_scores": {
      "full": 93.06930693069307,
      "label": 100,
      "keywords": 0.0,
      "final": 80.49707176600013
    },
    "page_number": 40,
    "node_index": 341,
    "start_node_index": 341,
    "end_node_index": 345,
    "start_page": 40,
    "end_page": 41,
    "alignment_score": 0.7924836601307189,
    "pdf_file_path": "C:\\Users\\mille\\OneDrive\\FDD_PDFS\\MINERU\\Budget_Blinds_LLC_FDD_2024_ID636427.pdf-96195de9-ed27-4de5-8f22-02f622605df9\\199524c0-3f73-405e-a873-9739e59be7e6_origin.pdf"
  },
  {
    "item_number": 17,
    "text": "ITEM 17. RENEWAL, TERMINATION, TRANSFER AND DISPUTE RESOLUTION",
    "match_scores": {
      "full": 97.6,
      "label": 100,
      "keywords": 0.0,
      "final": 83.6202614379085
    },
    "page_number": 41,
    "node_index": 346,
    "start_node_index": 346,
    "end_node_index": 353,
    "start_page": 41,
    "end_page": 43,
    "alignment_score": 0.9640522875816994,
    "pdf_file_path": "C:\\Users\\mille\\OneDrive\\FDD_PDFS\\MINERU\\Budget_Blinds_LLC_FDD_2024_ID636427.pdf-96195de9-ed27-4de5-8f22-02f622605df9\\199524c0-3f73-405e-a873-9739e59be7e6_origin.pdf"
  },
  {
    "item_number": 18,
    "text": "ITEM 18. PUBLIC FIGURES",
    "match_scores": {
      "full": 95.65217391304348,
      "label": 100,
      "keywords": 0.0,
      "final": 80.25255754475704
    },
    "page_number": 43,
    "node_index": 354,
    "start_node_index": 354,
    "end_node_index": 355,
    "start_page": 43,
    "end_page": 43,
    "alignment_score": 0.4852941176470589,
    "pdf_file_path": "C:\\Users\\mille\\OneDrive\\FDD_PDFS\\MINERU\\Budget_Blinds_LLC_FDD_2024_ID636427.pdf-96195de9-ed27-4de5-8f22-02f622605df9\\199524c0-3f73-405e-a873-9739e59be7e6_origin.pdf"
  },
  {
    "item_number": 19,
    "text": "ITEM 19. FINANCIAL PERFORMANCE REPRESENTATIONS",
    "match_scores": {
      "full": 97.82608695652173,
      "label": 100,
      "keywords": 0.0,
      "final": 82.84278204035238
    },
    "page_number": 43,
    "node_index": 356,
    "start_node_index": 356,
    "end_node_index": 375,
    "start_page": 43,
    "end_page": 47,
    "alignment_score": 0.7859477124183006,
    "pdf_file_path": "C:\\Users\\mille\\OneDrive\\FDD_PDFS\\MINERU\\Budget_Blinds_LLC_FDD_2024_ID636427.pdf-96195de9-ed27-4de5-8f22-02f622605df9\\199524c0-3f73-405e-a873-9739e59be7e6_origin.pdf"
  },
  {
    "item_number": 20,
    "text": "ITEM 20. OUTLETS AND FRANCHISEE INFORMATION",
    "match_scores": {
      "full": 97.67441860465117,
      "label": 100,
      "keywords": 0.0,
      "final": 83.73917008663932
    },
    "page_number": 47,
    "node_index": 376,
    "start_node_index": 376,
    "end_node_index": 417,
    "start_page": 47,
    "end_page": 60,
    "alignment_score": 0.9803921568627451,
    "pdf_file_path": "C:\\Users\\mille\\OneDrive\\FDD_PDFS\\MINERU\\Budget_Blinds_LLC_FDD_2024_ID636427.pdf-96195de9-ed27-4de5-8f22-02f622605df9\\199524c0-3f73-405e-a873-9739e59be7e6_origin.pdf"
  },
  {
    "item_number": 21,
    "text": "ITEM 21. FINANCIAL STATEMENTS",
    "match_scores": {
      "full": 96.55172413793103,
      "label": 100,
      "keywords": 0.0,
      "final": 81.11899932386748
    },
    "page_number": 60,
    "node_index": 418,
    "start_node_index": 418,
    "end_node_index": 419,
    "start_page": 60,
    "end_page": 60,
    "alignment_score": 0.5686274509803921,
    "pdf_file_path": "C:\\Users\\mille\\OneDrive\\FDD_PDFS\\MINERU\\Budget_Blinds_LLC_FDD_2024_ID636427.pdf-96195de9-ed27-4de5-8f22-02f622605df9\\199524c0-3f73-405e-a873-9739e59be7e6_origin.pdf"
  },
  {
    "item_number": 22,
    "text": "ITEM 22. CONTRACTS",
    "match_scores": {
      "full": 94.44444444444444,
      "label": 100,
      "keywords": 0.0,
      "final": 79.43627450980392
    },
    "page_number": 60,
    "node_index": 420,
    "start_node_index": 420,
    "end_node_index": 425,
    "start_page": 60,
    "end_page": 61,
    "alignment_score": 0.44281045751633985,
    "pdf_file_path": "C:\\Users\\mille\\OneDrive\\FDD_PDFS\\MINERU\\Budget_Blinds_LLC_FDD_2024_ID636427.pdf-96195de9-ed27-4de5-8f22-02f622605df9\\199524c0-3f73-405e-a873-9739e59be7e6_origin.pdf"
  },
  {
    "item_number": 23,
    "text": "ITEM 23. RECEIPT",
    "match_scores": {
      "full": 90.9090909090909,
      "label": 100,
      "keywords": 0.0,
      "final": 77.48068924539513
    },
    "page_number": 61,
    "node_index": 426,
    "start_node_index": 426,
    "end_node_index": 2046,
    "start_page": 61,
    "end_page": 281,
    "alignment_score": 0.40522875816993464,
    "pdf_file_path": "C:\\Users\\mille\\OneDrive\\FDD_PDFS\\MINERU\\Budget_Blinds_LLC_FDD_2024_ID636427.pdf-96195de9-ed27-4de5-8f22-02f622605df9\\199524c0-3f73-405e-a873-9739e59be7e6_origin.pdf"
  }
]